ChangeLog
LICENSE
MANIFEST.in
README.markdown
aliases
setup.py
gtdzen/__init__.py
gtdzen/client.py
gtdzen/exceptions.py
gtdzen/models.py
gtdzen/utils.py
gtdzen.egg-info/PKG-INFO
gtdzen.egg-info/SOURCES.txt
gtdzen.egg-info/dependency_links.txt
gtdzen.egg-info/entry_points.txt
gtdzen.egg-info/not-zip-safe
gtdzen.egg-info/requires.txt
gtdzen.egg-info/top_level.txt
gtdzen/migrations/__init__.py
gtdzen/migrations/manage.py
gtdzen/migrations/versions/001_sqlite_downgrade.sql
gtdzen/migrations/versions/001_sqlite_upgrade.sql
gtdzen/migrations/versions/002_sqlite_downgrade.sql
gtdzen/migrations/versions/002_sqlite_upgrade.sql
gtdzen/migrations/versions/__init__.py